[
  {
    "id": 1,
    "sport": "cross-country",
    "title": "Världscupen i Ruka",
    "competition": "10 km - Herrar",
    "channel": "TBA",
    "date": "2025-11-28",
    "time": "TBA",
    "description": "Världscuptävling i Ruka",
    "verified": false
  },
  {
    "id": 2,
    "sport": "cross-country",
    "title": "Världscupen i Ruka",
    "competition": "10 km - Damer",
    "channel": "TBA",
    "date": "2025-11-28",
    "time": "TBA",
    "description": "Världscuptävling i Ruka",
    "verified": false
  },
  {
    "id": 3,
    "sport": "cross-country",
    "title": "Världscupen i Ruka",
    "competition": "Sprint - Damer",
    "channel": "TBA",
    "date": "2025-11-29",
    "time": "TBA",
    "description": "Världscuptävling i Ruka",
    "verified": false
  },
  {
    "id": 4,
    "sport": "cross-country",
    "title": "Världscupen i Ruka",
    "competition": "Sprint - Herrar",
    "channel": "TBA",
    "date": "2025-11-29",
    "time": "TBA",
    "description": "Världscuptävling i Ruka",
    "verified": false
  },
  {
    "id": 5,
    "sport": "biathlon",
    "title": "Världscupen i Oestersund",
    "competition": "Världscup",
    "channel": "TBA",
    "date": "2025-11-29",
    "time": "TBA",
    "description": "Skidskytte-världscup i Oestersund",
    "verified": false
  },
  {
    "id": 6,
    "sport": "cross-country",
    "title": "Världscupen i Ruka",
    "competition": "30 km - Damer",
    "channel": "TBA",
    "date": "2025-11-30",
    "time": "TBA",
    "description": "Världscuptävling i Ruka",
    "verified": false
  },
  {
    "id": 7,
    "sport": "cross-country",
    "title": "Världscupen i Ruka",
    "competition": "30 km - Herrar",
    "channel": "TBA",
    "date": "2025-11-30",
    "time": "TBA",
    "description": "Världscuptävling i Ruka",
    "verified": false
  },
  {
    "id": 8,
    "sport": "cross-country",
    "title": "Världscupen i Trondheim",
    "competition": "Sprint - Herrar",
    "channel": "TBA",
    "date": "2025-12-05",
    "time": "TBA",
    "description": "Världscuptävling i Trondheim",
    "verified": false
  },
  {
    "id": 9,
    "sport": "cross-country",
    "title": "Världscupen i Trondheim",
    "competition": "Sprint - Damer",
    "channel": "TBA",
    "date": "2025-12-05",
    "time": "TBA",
    "description": "Världscuptävling i Trondheim",
    "verified": false
  },
  {
    "id": 10,
    "sport": "cross-country",
    "title": "Världscupen i Trondheim",
    "competition": "Skiatlon - Herrar",
    "channel": "TBA",
    "date": "2025-12-06",
    "time": "TBA",
    "description": "Världscuptävling i Trondheim",
    "verified": false
  },
  {
    "id": 11,
    "sport": "cross-country",
    "title": "Världscupen i Trondheim",
    "competition": "Skiatlon - Damer",
    "channel": "TBA",
    "date": "2025-12-06",
    "time": "TBA",
    "description": "Världscuptävling i Trondheim",
    "verified": false
  },
  {
    "id": 12,
    "sport": "cross-country",
    "title": "Världscupen i Trondheim",
    "competition": "10 km - Herrar",
    "channel": "TBA",
    "date": "2025-12-07",
    "time": "TBA",
    "description": "Världscuptävling i Trondheim",
    "verified": false
  },
  {
    "id": 13,
    "sport": "cross-country",
    "title": "Världscupen i Trondheim",
    "competition": "10 km - Damer",
    "channel": "TBA",
    "date": "2025-12-07",
    "time": "TBA",
    "description": "Världscuptävling i Trondheim",
    "verified": false
  },
  {
    "id": 14,
    "sport": "biathlon",
    "title": "Världscupen i Hochfilzen",
    "competition": "Världscup",
    "channel": "TBA",
    "date": "2025-12-08",
    "time": "TBA",
    "description": "Skidskytte-världscup i Hochfilzen",
    "verified": false
  },
  {
    "id": 15,
    "sport": "cross-country",
    "title": "Världscupen i Davos",
    "competition": "Teamsprint - Damer",
    "channel": "TBA",
    "date": "2025-12-12",
    "time": "TBA",
    "description": "Världscuptävling i Davos",
    "verified": false
  },
  {
    "id": 16,
    "sport": "cross-country",
    "title": "Världscupen i Davos",
    "competition": "Teamsprint - Herrar",
    "channel": "TBA",
    "date": "2025-12-12",
    "time": "TBA",
    "description": "Världscuptävling i Davos",
    "verified": false
  },
  {
    "id": 17,
    "sport": "cross-country",
    "title": "Världscupen i Davos",
    "competition": "Sprint - Herrar",
    "channel": "TBA",
    "date": "2025-12-13",
    "time": "TBA",
    "description": "Världscuptävling i Davos",
    "verified": false
  },
  {
    "id": 18,
    "sport": "cross-country",
    "title": "Världscupen i Davos",
    "competition": "Sprint - Damer",
    "channel": "TBA",
    "date": "2025-12-13",
    "time": "TBA",
    "description": "Världscuptävling i Davos",
    "verified": false
  },
  {
    "id": 19,
    "sport": "cross-country",
    "title": "Världscupen i Davos",
    "competition": "10 km - Herrar",
    "channel": "TBA",
    "date": "2025-12-14",
    "time": "TBA",
    "description": "Världscuptävling i Davos",
    "verified": false
  },
  {
    "id": 20,
    "sport": "cross-country",
    "title": "Världscupen i Davos",
    "competition": "10 km - Damer",
    "channel": "TBA",
    "date": "2025-12-14",
    "time": "TBA",
    "description": "Världscuptävling i Davos",
    "verified": false
  },
  {
    "id": 21,
    "sport": "biathlon",
    "title": "Världscupen i Annecy-Le Grand Bornand",
    "competition": "Världscup",
    "channel": "TBA",
    "date": "2025-12-15",
    "time": "TBA",
    "description": "Skidskytte-världscup i Annecy-Le Grand Bornand",
    "verified": false
  },
  {
    "id": 22,
    "sport": "cross-country",
    "title": "Världscupen i Tour de Ski",
    "competition": "50 km - Damer",
    "channel": "TBA",
    "date": "2026-01-04",
    "time": "TBA",
    "description": "Världscuptävling i Tour de Ski",
    "verified": false
  },
  {
    "id": 23,
    "sport": "cross-country",
    "title": "Världscupen i Tour de Ski",
    "competition": "50 km - Herrar",
    "channel": "TBA",
    "date": "2026-01-04",
    "time": "TBA",
    "description": "Världscuptävling i Tour de Ski",
    "verified": false
  },
  {
    "id": 24,
    "sport": "biathlon",
    "title": "Världscupen i Oberhof",
    "competition": "Världscup",
    "channel": "TBA",
    "date": "2026-01-05",
    "time": "TBA",
    "description": "Skidskytte-världscup i Oberhof",
    "verified": false
  },
  {
    "id": 25,
    "sport": "biathlon",
    "title": "Världscupen i Ruhpolding",
    "competition": "Världscup",
    "channel": "TBA",
    "date": "2026-01-12",
    "time": "TBA",
    "description": "Skidskytte-världscup i Ruhpolding",
    "verified": false
  },
  {
    "id": 26,
    "sport": "cross-country",
    "title": "Världscupen i Oberhof",
    "competition": "Sprint - Damer",
    "channel": "TBA",
    "date": "2026-01-17",
    "time": "TBA",
    "description": "Världscuptävling i Oberhof",
    "verified": false
  },
  {
    "id": 27,
    "sport": "cross-country",
    "title": "Världscupen i Oberhof",
    "competition": "Sprint - Herrar",
    "channel": "TBA",
    "date": "2026-01-17",
    "time": "TBA",
    "description": "Världscuptävling i Oberhof",
    "verified": false
  },
  {
    "id": 28,
    "sport": "cross-country",
    "title": "Världscupen i Oberhof",
    "competition": "10 km - Damer",
    "channel": "TBA",
    "date": "2026-01-18",
    "time": "TBA",
    "description": "Världscuptävling i Oberhof",
    "verified": false
  },
  {
    "id": 29,
    "sport": "cross-country",
    "title": "Världscupen i Oberhof",
    "competition": "10 km - Herrar",
    "channel": "TBA",
    "date": "2026-01-18",
    "time": "TBA",
    "description": "Världscuptävling i Oberhof",
    "verified": false
  },
  {
    "id": 30,
    "sport": "biathlon",
    "title": "Världscupen i Nove Mesto na Morave",
    "competition": "Världscup",
    "channel": "TBA",
    "date": "2026-01-19",
    "time": "TBA",
    "description": "Skidskytte-världscup i Nove Mesto na Morave",
    "verified": false
  },
  {
    "id": 31,
    "sport": "cross-country",
    "title": "Världscupen i Goms",
    "competition": "Teamsprint - Herrar",
    "channel": "TBA",
    "date": "2026-01-23",
    "time": "TBA",
    "description": "Världscuptävling i Goms",
    "verified": false
  },
  {
    "id": 32,
    "sport": "cross-country",
    "title": "Världscupen i Goms",
    "competition": "Teamsprint - Damer",
    "channel": "TBA",
    "date": "2026-01-23",
    "time": "TBA",
    "description": "Världscuptävling i Goms",
    "verified": false
  },
  {
    "id": 33,
    "sport": "cross-country",
    "title": "Världscupen i Goms",
    "competition": "Sprint - Herrar",
    "channel": "TBA",
    "date": "2026-01-24",
    "time": "TBA",
    "description": "Världscuptävling i Goms",
    "verified": false
  },
  {
    "id": 34,
    "sport": "cross-country",
    "title": "Världscupen i Goms",
    "competition": "Sprint - Damer",
    "channel": "TBA",
    "date": "2026-01-24",
    "time": "TBA",
    "description": "Världscuptävling i Goms",
    "verified": false
  },
  {
    "id": 35,
    "sport": "cross-country",
    "title": "Världscupen i Goms",
    "competition": "30 km - Herrar",
    "channel": "TBA",
    "date": "2026-01-25",
    "time": "TBA",
    "description": "Världscuptävling i Goms",
    "verified": false
  },
  {
    "id": 36,
    "sport": "cross-country",
    "title": "Världscupen i Goms",
    "competition": "30 km - Damer",
    "channel": "TBA",
    "date": "2026-01-25",
    "time": "TBA",
    "description": "Världscuptävling i Goms",
    "verified": false
  },
  {
    "id": 37,
    "sport": "biathlon",
    "title": "Världscupen i Antholz-Anterselva",
    "competition": "Världscup",
    "channel": "TBA",
    "date": "2026-02-06",
    "time": "TBA",
    "description": "Skidskytte-världscup i Antholz-Anterselva",
    "verified": false
  },
  {
    "id": 38,
    "sport": "cross-country",
    "title": "Världscupen i Falun",
    "competition": "Sprint - Herrar",
    "channel": "TBA",
    "date": "2026-02-28",
    "time": "TBA",
    "description": "Världscuptävling i Falun",
    "verified": false
  },
  {
    "id": 39,
    "sport": "cross-country",
    "title": "Världscupen i Falun",
    "competition": "Sprint - Damer",
    "channel": "TBA",
    "date": "2026-02-28",
    "time": "TBA",
    "description": "Världscuptävling i Falun",
    "verified": false
  },
  {
    "id": 40,
    "sport": "cross-country",
    "title": "Världscupen i Falun",
    "competition": "Skiatlon - Herrar",
    "channel": "TBA",
    "date": "2026-03-01",
    "time": "TBA",
    "description": "Världscuptävling i Falun",
    "verified": false
  },
  {
    "id": 41,
    "sport": "cross-country",
    "title": "Världscupen i Falun",
    "competition": "Skiatlon - Damer",
    "channel": "TBA",
    "date": "2026-03-01",
    "time": "TBA",
    "description": "Världscuptävling i Falun",
    "verified": false
  },
  {
    "id": 42,
    "sport": "biathlon",
    "title": "Världscupen i Kontiolahti",
    "competition": "Världscup",
    "channel": "TBA",
    "date": "2026-03-02",
    "time": "TBA",
    "description": "Skidskytte-världscup i Kontiolahti",
    "verified": false
  },
  {
    "id": 43,
    "sport": "cross-country",
    "title": "Världscupen i Lahti",
    "competition": "Sprint - Damer",
    "channel": "TBA",
    "date": "2026-03-07",
    "time": "TBA",
    "description": "Världscuptävling i Lahti",
    "verified": false
  },
  {
    "id": 44,
    "sport": "cross-country",
    "title": "Världscupen i Lahti",
    "competition": "Sprint - Herrar",
    "channel": "TBA",
    "date": "2026-03-07",
    "time": "TBA",
    "description": "Världscuptävling i Lahti",
    "verified": false
  },
  {
    "id": 45,
    "sport": "cross-country",
    "title": "Världscupen i Lahti",
    "competition": "10 km - Damer",
    "channel": "TBA",
    "date": "2026-03-08",
    "time": "TBA",
    "description": "Världscuptävling i Lahti",
    "verified": false
  },
  {
    "id": 46,
    "sport": "cross-country",
    "title": "Världscupen i Lahti",
    "competition": "10 km - Herrar",
    "channel": "TBA",
    "date": "2026-03-08",
    "time": "TBA",
    "description": "Världscuptävling i Lahti",
    "verified": false
  },
  {
    "id": 47,
    "sport": "biathlon",
    "title": "Världscupen i Otepaa",
    "competition": "Världscup",
    "channel": "TBA",
    "date": "2026-03-09",
    "time": "TBA",
    "description": "Skidskytte-världscup i Otepaa",
    "verified": false
  },
  {
    "id": 48,
    "sport": "cross-country",
    "title": "Världscupen i Drammen",
    "competition": "Sprint - Damer",
    "channel": "TBA",
    "date": "2026-03-12",
    "time": "TBA",
    "description": "Världscuptävling i Drammen",
    "verified": false
  },
  {
    "id": 49,
    "sport": "cross-country",
    "title": "Världscupen i Drammen",
    "competition": "Sprint - Herrar",
    "channel": "TBA",
    "date": "2026-03-12",
    "time": "TBA",
    "description": "Världscuptävling i Drammen",
    "verified": false
  },
  {
    "id": 50,
    "sport": "cross-country",
    "title": "Världscupen i Oslo",
    "competition": "50 km - Herrar",
    "channel": "TBA",
    "date": "2026-03-14",
    "time": "TBA",
    "description": "Världscuptävling i Oslo",
    "verified": false
  },
  {
    "id": 51,
    "sport": "cross-country",
    "title": "Världscupen i Oslo",
    "competition": "50 km - Damer",
    "channel": "TBA",
    "date": "2026-03-14",
    "time": "TBA",
    "description": "Världscuptävling i Oslo",
    "verified": false
  },
  {
    "id": 52,
    "sport": "biathlon",
    "title": "Världscupen i Oslo Holmenkollen",
    "competition": "Världscup",
    "channel": "TBA",
    "date": "2026-03-16",
    "time": "TBA",
    "description": "Skidskytte-världscup i Oslo Holmenkollen",
    "verified": false
  },
  {
    "id": 53,
    "sport": "cross-country",
    "title": "Världscupen i Lake Placid",
    "competition": "10 km - Damer",
    "channel": "TBA",
    "date": "2026-03-20",
    "time": "TBA",
    "description": "Världscuptävling i Lake Placid",
    "verified": false
  },
  {
    "id": 54,
    "sport": "cross-country",
    "title": "Världscupen i Lake Placid",
    "competition": "10 km - Herrar",
    "channel": "TBA",
    "date": "2026-03-20",
    "time": "TBA",
    "description": "Världscuptävling i Lake Placid",
    "verified": false
  },
  {
    "id": 55,
    "sport": "cross-country",
    "title": "Världscupen i Lake Placid",
    "competition": "Sprint - Damer",
    "channel": "TBA",
    "date": "2026-03-21",
    "time": "TBA",
    "description": "Världscuptävling i Lake Placid",
    "verified": false
  },
  {
    "id": 56,
    "sport": "cross-country",
    "title": "Världscupen i Lake Placid",
    "competition": "Sprint - Herrar",
    "channel": "TBA",
    "date": "2026-03-21",
    "time": "TBA",
    "description": "Världscuptävling i Lake Placid",
    "verified": false
  },
  {
    "id": 57,
    "sport": "cross-country",
    "title": "Världscupen i Lake Placid",
    "competition": "30 km - Damer",
    "channel": "TBA",
    "date": "2026-03-22",
    "time": "TBA",
    "description": "Världscuptävling i Lake Placid",
    "verified": false
  },
  {
    "id": 58,
    "sport": "cross-country",
    "title": "Världscupen i Lake Placid",
    "competition": "30 km - Herrar",
    "channel": "TBA",
    "date": "2026-03-22",
    "time": "TBA",
    "description": "Världscuptävling i Lake Placid",
    "verified": false
  }
]